enscons/__init__.py
enscons/api.py
enscons/cli.py
enscons/cpyext.py
enscons/paths.py
enscons/pytar.py
enscons/setup.py
enscons/setup2toml.py
enscons/toml.py
enscons/util.py
enscons/SConstruct.in
enscons-0.30.0.dist-info/METADATA
enscons-0.30.0.dist-info/WHEEL
enscons-0.30.0.dist-info/entry_points.txt
enscons-0.30.0.dist-info/RECORD