Metadata-Version: 2.1
Name: enscons
Version: 0.30.0
Summary: Tools for building Python packages with SCons
License: MIT
Author: Daniel Holth
Author-email: dholth@fastmail.fm
Keywords: packaging,wheel
Classifier: Programming Language :: Python :: 3
Home-Page: https://github.com/dholth/enscons
Provides-Extra: cli
Requires-Dist: click; extra == 'cli'
Provides-Extra: docs
Requires-Dist: furo; extra == 'docs'
Requires-Dist: sphinx; extra == 'docs'
Requires-Dist: myst-parser; extra == 'docs'
Requires-Dist: mdit-py-plugins>=0.3.0; extra == 'docs'
Requires-Dist: scons>=3.0.5
Requires-Dist: tomli; python_version < "3.11"
Requires-Dist: setuptools
Requires-Dist: wheel
Requires-Dist: attrs
Requires-Dist: packaging>=20.9
Requires-Dist: editables
